docs/commands/commands.rst
docs/commands/sbench.rst
docs/commands/sbl.rst
docs/commands/sboard.rst
docs/commands/scard.rst
docs/commands/svalid.rst
docs/images/logo.png
docs/source/modules.rst
docs/source/scrummd.rst
docs/tutorial_examples/tutorial1/scrum/backlog/card1.md
docs/tutorial_examples/tutorial1/scrum/reports/bug1.md
docs/tutorial_examples/tutorial1.2/scrum/backlog/card1.md
docs/tutorial_examples/tutorial1.2/scrum/reports/bug1.md
docs/tutorial_examples/tutorial1.2/scrum/reports/bug2.md
docs/tutorial_examples/tutorial1.2/scrum/reports/bug3.md
docs/tutorial_examples/tutorial1.3/scrum/backlog/card1.md
docs/tutorial_examples/tutorial1.3/scrum/reports/bug1.md
docs/tutorial_examples/tutorial1.3/scrum/reports/bug2.md
docs/tutorial_examples/tutorial1.3/scrum/reports/bug3.md
docs/tutorial_examples/tutorial1.4/scrum.toml
docs/tutorial_examples/tutorial1.4/scrum/backlog/card1.md
docs/tutorial_examples/tutorial1.4/scrum/reports/bug1.md
docs/tutorial_examples/tutorial1.4/scrum/reports/bug2.md
docs/tutorial_examples/tutorial1.4/scrum/reports/bug3.md
docs/tutorial_examples/tutorial1.4/scrum/reports/bug4.md
docs/tutorial_examples/tutorial1.5/scrum.toml
docs/tutorial_examples/tutorial1.5/scrum/backlog/card1.md
docs/tutorial_examples/tutorial1.5/scrum/reports/bug1.md
docs/tutorial_examples/tutorial1.5/scrum/reports/bug2.md
docs/tutorial_examples/tutorial1.5/scrum/reports/bug3.md
docs/tutorial_examples/tutorial1.6/scrum.toml
docs/tutorial_examples/tutorial1.6/scrum/backlog/card1.md
docs/tutorial_examples/tutorial1.6/scrum/reports/bug1.md
docs/tutorial_examples/tutorial1.6/scrum/reports/bug2.md
docs/tutorial_examples/tutorial1.6/scrum/reports/bug3.md
scrum/bugs/cli019.md
scrum/bugs/cli026.md
scrum/stories/cli001.md
scrum/stories/cli002.md
scrum/stories/cli003.md
scrum/stories/cli004.md
scrum/stories/cli005.md
scrum/stories/cli006.md
scrum/stories/cli007.md
scrum/stories/cli008.md
scrum/stories/cli009.md
scrum/stories/cli010.md
scrum/stories/cli011.md
scrum/stories/cli012.md
scrummd-0.1.2.dist-info/LICENSE.md
scrummd-0.1.2.dist-info/METADATA
scrummd-0.1.2.dist-info/WHEEL
scrummd-0.1.2.dist-info/entry_points.txt
scrummd-0.1.2.dist-info/top_level.txt
scrummd-0.1.2.dist-info/RECORD
