Metadata-Version: 2.1
Name: scrummd
Version: 0.1.2
Author-email: Lachlan Kingsford <lachlan@nerdygentleman.com>
Requires-Python: >=3.10
License-File: LICENSE.md
Requires-Dist: tomli ; python_version < "3.11"
